soap/__init__.py
soap/http.py
soap/settings.py
soap/test.py
soap/tests/__init__.py
soap/tests/test_soap.py
instrumented_soap-2.1.2.dist-info/LICENSE.md
instrumented_soap-2.1.2.dist-info/METADATA
instrumented_soap-2.1.2.dist-info/WHEEL
instrumented_soap-2.1.2.dist-info/RECORD
