Metadata-Version: 2.1
Name: instrumented-soap
Version: 2.1.2
Summary: Wrapper around suds-community that adds improved proxy support and testing tools.
Home-page: https://gitlab.com/thelabnyc/instrumented-soap
License: ISC
Author: thelab
Author-email: thelabdev@thelab.co
Requires-Python: >=3.10,<4.0
Classifier: License :: OSI Approved
Classifier: Programming Language :: Python :: 3
Classifier: Programming Language :: Python :: 3.10
Classifier: Programming Language :: Python :: 3.11
Classifier: Programming Language :: Python :: 3.12
Requires-Dist: Django (>=4.2)
Requires-Dist: requests (>=2.32.3)
Requires-Dist: suds-community (>=1.2.0)
Project-URL: Repository, https://gitlab.com/thelabnyc/instrumented-soap
